mccalcy/__init__.py
mccalcy/mccalcy.py
mccalcy-0.0.15.dist-info/LICENSE
mccalcy-0.0.15.dist-info/WHEEL
mccalcy-0.0.15.dist-info/METADATA
mccalcy-0.0.15.dist-info/RECORD
