Metadata-Version: 2.1
Name: mccalcy
Version: 0.0.15
Summary: A small test package with calculator module.
Author-email: Vitalijus <vitalijus.kiubis@gmail.com>
Requires-Python: >=3.7
Classifier: License :: OSI Approved :: MIT License
Project-URL: Home, https://github.com/VitalijusKiubis/mccalcy
